rcount.py
setup.py
rcount.egg-info/PKG-INFO
rcount.egg-info/SOURCES.txt
rcount.egg-info/dependency_links.txt
rcount.egg-info/not-zip-safe
rcount.egg-info/top_level.txt