Metadata-Version: 1.0
Name: rcount
Version: 0.0.1
Summary: Redis-powered counting, comparing, and ranking
Home-page: http://github.com/tnm/rcount
Author: Ted Nyman
Author-email: tnm800@gmail.com
License: MIT
Keywords: Redis,counting,increment,ranking data structures
Platform: UNKNOWN
Classifier: Programming Language :: Python
Classifier: Intended Audience :: Developers
Classifier: License :: OSI Approved :: MIT License
Classifier: Operating System :: OS Independent
